byted_overpass_toutiao_search_search_suggest_words/__init__.py
byted_overpass_toutiao_search_search_suggest_words-0.0.1.dist-info/METADATA
byted_overpass_toutiao_search_search_suggest_words-0.0.1.dist-info/WHEEL
byted_overpass_toutiao_search_search_suggest_words-0.0.1.dist-info/top_level.txt
byted_overpass_toutiao_search_search_suggest_words-0.0.1.dist-info/RECORD
